clinical_zeroshot_labeler/__init__.py
clinical_zeroshot_labeler/labeler.py
clinical_zeroshot_labeler/model.py
clinical_zeroshot_labeler-0.0.3.dist-info/LICENSE
clinical_zeroshot_labeler-0.0.3.dist-info/METADATA
clinical_zeroshot_labeler-0.0.3.dist-info/WHEEL
clinical_zeroshot_labeler-0.0.3.dist-info/top_level.txt
clinical_zeroshot_labeler-0.0.3.dist-info/RECORD
