Metadata-Version: 2.1
Name: clinical_zeroshot_labeler
Version: 0.0.3
Summary: A MEDS PyTorch Dataset, leveraging a on-the-fly retrieval strategy for flexible, efficient data loading.
Author-email: Matthew McDermott <mattmcdermott8@gmail.com>, Nassim Oufattole <noufattole@gmail.com>, Teya Bergamaschi <teyabergamaschi@gmail.com>, Aleksia Kolo <aleksiakolo@gmail.com>
Project-URL: Homepage, https://github.com/oufattole/clinical-zeroshot-labeler
Project-URL: Issues, https://github.com/oufattole/clinical-zeroshot-labeler/issues
Classifier: Programming Language :: Python :: 3
Classifier: License :: OSI Approved :: MIT License
Classifier: Operating System :: OS Independent
Requires-Python: >=3.11
License-File: LICENSE
Requires-Dist: polars
Requires-Dist: pyarrow
Requires-Dist: omegaconf
Requires-Dist: hydra-core
Requires-Dist: rich
Requires-Dist: hydra-colorlog
Requires-Dist: loguru
Requires-Dist: pytimeparse==1.1.*
Requires-Dist: networkx==3.3.*
Requires-Dist: bigtree==0.18.*
Requires-Dist: ruamel.yaml==0.18.*
Requires-Dist: torch
Requires-Dist: numpy
Requires-Dist: es-aces
Requires-Dist: x-transformers
Provides-Extra: dev
Requires-Dist: pre-commit<4; extra == "dev"
Requires-Dist: notebook; extra == "dev"
Requires-Dist: pdbpp; extra == "dev"
Provides-Extra: tests
Requires-Dist: pytest; extra == "tests"
Requires-Dist: pytest-cov[toml]; extra == "tests"
Requires-Dist: rootutils; extra == "tests"
Requires-Dist: pytest-sugar; extra == "tests"
Requires-Dist: pytest-instafail; extra == "tests"
Requires-Dist: pytest-xdist; extra == "tests"
Requires-Dist: sh; extra == "tests"
